visionsuite/__init__.py
visionsuite/agent.py
visionsuite/apis/__init__.py
visionsuite/cores/__init__.py
visionsuite/cores/athena/__init__.py
visionsuite/cores/athena/cls/__init__.py
visionsuite/cores/athena/cls/predict_cls_tf.py
visionsuite/cores/athena/det/__init__.py
visionsuite/cores/athena/det/predict_det_torch.py
visionsuite/cores/athena/det/predict_det_torch_patch.py
visionsuite/cores/athena/obbdet/__init__.py
visionsuite/cores/athena/obbdet/test.py
visionsuite/cores/athena/seg/__init__.py
visionsuite/cores/athena/seg/predict_seg_tf.py
visionsuite/cores/athena/seg/predict_seg_torch.py
visionsuite/cores/athena/seg/test_tf_patch.py
visionsuite/cores/caps/__init__.py
visionsuite/cores/contmav/__init__.py
visionsuite/cores/contmav/test.py
visionsuite/cores/contmav/train.py
visionsuite/cores/contmav/src/__init__.py
visionsuite/cores/contmav/src/args.py
visionsuite/cores/contmav/src/args_test.py
visionsuite/cores/contmav/src/build_model.py
visionsuite/cores/contmav/src/contrastive_loss.py
visionsuite/cores/contmav/src/prepare_data.py
visionsuite/cores/contmav/src/preprocessing.py
visionsuite/cores/contmav/src/utils.py
visionsuite/cores/contmav/src/datasets/__init__.py
visionsuite/cores/contmav/src/datasets/dataset_base.py
visionsuite/cores/contmav/src/datasets/cityscapes/__init__.py
visionsuite/cores/contmav/src/datasets/cityscapes/cityscapes.py
visionsuite/cores/contmav/src/datasets/cityscapes/prepare_dataset.py
visionsuite/cores/contmav/src/datasets/cityscapes/pytorch_dataset.py
visionsuite/cores/masked_autoencoder/__init__.py
visionsuite/cores/masked_autoencoder/demo.py
visionsuite/cores/masked_autoencoder/utils/__init__.py
visionsuite/cores/roboflow/__init__.py
visionsuite/cores/roboflow/configs/__init__.py
visionsuite/cores/roboflow/configs/export_config.py
visionsuite/cores/roboflow/configs/test_config.py
visionsuite/cores/roboflow/configs/train_config.py
visionsuite/cores/roboflow/configs/train_config_rtdetr.py
visionsuite/cores/roboflow/scripts/__init__.py
visionsuite-1.0.24.dist-info/METADATA
visionsuite-1.0.24.dist-info/WHEEL
visionsuite-1.0.24.dist-info/top_level.txt
visionsuite-1.0.24.dist-info/RECORD
