Metadata-Version: 2.4
Name: visionsuite
Version: 1.0.24
Summary: Template for Python Athena
Requires-Python: >=3.9
Requires-Dist: pydantic
Requires-Dist: omegaconf
Requires-Dist: pyyaml==5.3.1
Requires-Dist: nvidia-ml-py3
Dynamic: description
Dynamic: description-content-type
Dynamic: requires-dist
Dynamic: requires-python
Dynamic: summary
